gitlab_helper/AccessControlHelper.py
gitlab_helper/CloneSyncHelper.py
gitlab_helper/__init__.py
gitlab_superb_helper-1.0.0.dist-info/METADATA
gitlab_superb_helper-1.0.0.dist-info/WHEEL
gitlab_superb_helper-1.0.0.dist-info/top_level.txt
gitlab_superb_helper-1.0.0.dist-info/RECORD
