Metadata-Version: 2.1
Name: gitlab-superb-helper
Version: 1.0.0
Summary: Projeto para ser utilizado como Helper para o GitLab
Home-page: UNKNOWN
Author: Renan Ben Moshe
Author-email: renan.moshe@gmail.com
License: UNKNOWN
Platform: UNKNOWN
Classifier: Programming Language :: Python
Classifier: Programming Language :: Python :: 3.5
Classifier: Programming Language :: Python :: 3.6
Classifier: Topic :: Software Development :: Libraries
Classifier: Topic :: Software Development :: Libraries :: Python Modules
Classifier: Intended Audience :: Developers
Requires-Python: >=3.5
